mlswarm/__init__.py
mlswarm/mlswarm.py
mlswarm/neural_networks.py
mlswarm/optimizers.py
mlswarm/train.py
mlswarm/utils.py
mlswarm-0.33.dist-info/METADATA
mlswarm-0.33.dist-info/WHEEL
mlswarm-0.33.dist-info/top_level.txt
mlswarm-0.33.dist-info/RECORD
